infi.greeter-0.0.12-py2.7-nspkg.pth
infi/greeter/__init__.py
infi/greeter/__version__.py
infi/greeter/greeter.py
infi/greeter/install.py
infi/greeter/scripts.py
infi.greeter-0.0.12.dist-info/LICENSE
infi.greeter-0.0.12.dist-info/METADATA
infi.greeter-0.0.12.dist-info/WHEEL
infi.greeter-0.0.12.dist-info/entry_points.txt
infi.greeter-0.0.12.dist-info/namespace_packages.txt
infi.greeter-0.0.12.dist-info/top_level.txt
infi.greeter-0.0.12.dist-info/RECORD
